README.txt
mungempo.py
setup.py
mungempo.egg-info/PKG-INFO
mungempo.egg-info/SOURCES.txt
mungempo.egg-info/dependency_links.txt
mungempo.egg-info/entry_points.txt
mungempo.egg-info/requires.txt
mungempo.egg-info/top_level.txt