Metadata-Version: 1.1
Name: mungempo
Version: 0.1
Summary: Commandline tool/module for extracting stereo images from.MPO format files
Home-page: https://sourceforge.net/projects/mungempo/
Author: Nick Veitch
Author-email: nick@evilnick.org
License: GPLv3
Keywords: 3D graphics .MPO stereoscopic anaglyph
Platform: UNKNOWN
Provides: mungempo
